mlresearch/__init__.py
mlresearch/_min_dependencies.py
mlresearch/_version.py
mlresearch/active_learning/__init__.py
mlresearch/active_learning/_acquisition_functions.py
mlresearch/active_learning/_active_learning.py
mlresearch/active_learning/_deep_al.py
mlresearch/active_learning/base.py
mlresearch/active_learning/tests/__init__.py
mlresearch/active_learning/tests/test_acquisition_functions.py
mlresearch/active_learning/tests/test_active_learning_models.py
mlresearch/datasets/__init__.py
mlresearch/datasets/_binary.py
mlresearch/datasets/_multiclass.py
mlresearch/datasets/_remote_sensing.py
mlresearch/datasets/base.py
mlresearch/datasets/tests/__init__.py
mlresearch/datasets/tests/test_datasets.py
mlresearch/latex/__init__.py
mlresearch/latex/_utils.py
mlresearch/latex/tests/__init__.py
mlresearch/latex/tests/test_utils.py
mlresearch/metrics/__init__.py
mlresearch/metrics/_metrics.py
mlresearch/metrics/_rankings.py
mlresearch/metrics/_synth_data_quality.py
mlresearch/metrics/tests/__init__.py
mlresearch/metrics/tests/test_metrics.py
mlresearch/metrics/tests/test_synth_data_quality.py
mlresearch/model_selection/__init__.py
mlresearch/model_selection/_search.py
mlresearch/model_selection/_search_successive_halving.py
mlresearch/model_selection/tests/__init__.py
mlresearch/model_selection/tests/test_search.py
mlresearch/model_selection/tests/test_successive_halving.py
mlresearch/neural_network/__init__.py
mlresearch/neural_network/_one_class_mlp.py
mlresearch/preprocessing/__init__.py
mlresearch/preprocessing/_encoders.py
mlresearch/preprocessing/tests/__init__.py
mlresearch/preprocessing/tests/test_pipeline_encoder.py
mlresearch/synthetic_data/__init__.py
mlresearch/synthetic_data/_gsmote.py
mlresearch/synthetic_data/_oversampling_augmentation.py
mlresearch/synthetic_data/tests/__init__.py
mlresearch/synthetic_data/tests/test_gsmote.py
mlresearch/synthetic_data/tests/test_oversampling_augmentation.py
mlresearch/tests/__init__.py
ml_research-0.5.2.dist-info/LICENSE
ml_research-0.5.2.dist-info/METADATA
ml_research-0.5.2.dist-info/WHEEL
ml_research-0.5.2.dist-info/top_level.txt
ml_research-0.5.2.dist-info/RECORD
