Metadata-Version: 2.1
Name: ml-research
Version: 0.5.2
Summary: Implementation of Machine Learning algorithms, experiments and utilities.
Home-page: https://github.com/joaopfonseca/ml-research
Download-URL: https://github.com/joaopfonseca/ml-research
Maintainer: J. Fonseca
Maintainer-email: jpfonseca@novaims.unl.pt
License: MIT
Classifier: Intended Audience :: Science/Research
Classifier: Intended Audience :: Developers
Classifier: License :: OSI Approved
Classifier: Programming Language :: Python
Classifier: Topic :: Software Development
Classifier: Topic :: Scientific/Engineering
Classifier: Operating System :: Microsoft :: Windows
Classifier: Operating System :: POSIX
Classifier: Operating System :: Unix
Classifier: Operating System :: MacOS
Classifier: Programming Language :: Python :: 3.10
Classifier: Programming Language :: Python :: 3.11
Classifier: Programming Language :: Python :: 3.12
Classifier: Programming Language :: Python :: 3.13
License-File: LICENSE
Requires-Dist: pandas>=2.1.0
Requires-Dist: numpy>=1.20.0
Requires-Dist: scikit-learn>=1.2.0
Requires-Dist: imbalanced-learn>=0.8.0
Requires-Dist: requests>=2.26.0
Provides-Extra: optional
Requires-Dist: tqdm>=4.46.0; extra == "optional"
Requires-Dist: matplotlib>=2.2.3; extra == "optional"
Provides-Extra: docs
Requires-Dist: matplotlib>=2.2.3; extra == "docs"
Requires-Dist: numpydoc>=1.0.0; extra == "docs"
Requires-Dist: sphinx>=4.2.0; extra == "docs"
Requires-Dist: sphinx-material>=0.0.35; extra == "docs"
Requires-Dist: recommonmark>=0.7.1; extra == "docs"
Requires-Dist: sphinx-markdown-tables>=0.0.15; extra == "docs"
Requires-Dist: sphinx-copybutton>=0.4.0; extra == "docs"
Requires-Dist: sphinx-gallery>=0.17.1; extra == "docs"
Requires-Dist: ipykernel>=6.29.5; extra == "docs"
Requires-Dist: pandoc>=2.4; extra == "docs"
Provides-Extra: examples
Provides-Extra: tests
Requires-Dist: pytest-cov>=3.0.0; extra == "tests"
Requires-Dist: flake8>=3.8.2; extra == "tests"
Requires-Dist: black>=22.3; extra == "tests"
Requires-Dist: pylint>=2.12.2; extra == "tests"
Requires-Dist: mypy>=1.6.1; extra == "tests"
Requires-Dist: types-requests>=2.31.0.10; extra == "tests"
Requires-Dist: coverage>=6.2; extra == "tests"
Requires-Dist: numpydoc>=1.0.0; extra == "tests"
Provides-Extra: all
Requires-Dist: pandas>=2.1.0; extra == "all"
Requires-Dist: numpy>=1.20.0; extra == "all"
Requires-Dist: scikit-learn>=1.2.0; extra == "all"
Requires-Dist: imbalanced-learn>=0.8.0; extra == "all"
Requires-Dist: requests>=2.26.0; extra == "all"
Requires-Dist: tqdm>=4.46.0; extra == "all"
Requires-Dist: matplotlib>=2.2.3; extra == "all"
Requires-Dist: pytest-cov>=3.0.0; extra == "all"
Requires-Dist: flake8>=3.8.2; extra == "all"
Requires-Dist: black>=22.3; extra == "all"
Requires-Dist: pylint>=2.12.2; extra == "all"
Requires-Dist: mypy>=1.6.1; extra == "all"
Requires-Dist: types-requests>=2.31.0.10; extra == "all"
Requires-Dist: coverage>=6.2; extra == "all"
Requires-Dist: numpydoc>=1.0.0; extra == "all"
Requires-Dist: sphinx>=4.2.0; extra == "all"
Requires-Dist: sphinx-material>=0.0.35; extra == "all"
Requires-Dist: recommonmark>=0.7.1; extra == "all"
Requires-Dist: sphinx-markdown-tables>=0.0.15; extra == "all"
Requires-Dist: sphinx-copybutton>=0.4.0; extra == "all"
Requires-Dist: sphinx-gallery>=0.17.1; extra == "all"
Requires-Dist: ipykernel>=6.29.5; extra == "all"
Requires-Dist: pandoc>=2.4; extra == "all"
